anodetection/__init__.py
anodetection/car_workflow.py
workflow_upa-0.0.2.dist-info/METADATA
workflow_upa-0.0.2.dist-info/WHEEL
workflow_upa-0.0.2.dist-info/top_level.txt
workflow_upa-0.0.2.dist-info/RECORD
